LICENSE
README.md
pyproject.toml
domselect/__init__.py
domselect/base.py
domselect/errors.py
domselect/lexbor_selector.py
domselect/lxml_selector.py
domselect/py.typed
domselect/unset.py
domselect.egg-info/PKG-INFO
domselect.egg-info/SOURCES.txt
domselect.egg-info/dependency_links.txt
domselect.egg-info/top_level.txt
tests/test_lexbor_selector.py
tests/test_xpath_selector.py